gstaichi/__init__.py
gstaichi/_funcs.py
gstaichi/_kernels.py
gstaichi/_logging.py
gstaichi/_version.py
gstaichi/experimental.py
gstaichi/_lib/__init__.py
gstaichi/_lib/utils.py
gstaichi/_lib/core/__init__.py
gstaichi/_lib/core/gstaichi_python.cpython-313-darwin.so
gstaichi/_lib/core/gstaichi_python.pyi
gstaichi/_lib/core/py.typed
gstaichi/_lib/runtime/libMoltenVK.dylib
gstaichi/_lib/runtime/runtime_arm64.bc
gstaichi/_snode/__init__.py
gstaichi/_snode/fields_builder.py
gstaichi/_snode/snode_tree.py
gstaichi/_test_tools/__init__.py
gstaichi/_test_tools/dataclass_test_tools.py
gstaichi/_test_tools/load_kernel_string.py
gstaichi/_test_tools/textwrap2.py
gstaichi/_test_tools/warnings_helper.py
gstaichi/ad/__init__.py
gstaichi/ad/_ad.py
gstaichi/algorithms/__init__.py
gstaichi/algorithms/_algorithms.py
gstaichi/assets/.git
gstaichi/assets/Go-Regular.ttf
gstaichi/assets/static/imgs/ti_gallery.png
gstaichi/examples/lcg_python.py
gstaichi/examples/lcg_taichi.py
gstaichi/examples/minimal.py
gstaichi/lang/__init__.py
gstaichi/lang/_dataclass_util.py
gstaichi/lang/_func_base.py
gstaichi/lang/_gstaichi_callable.py
gstaichi/lang/_kernel_impl_dataclass.py
gstaichi/lang/_kernel_types.py
gstaichi/lang/_ndarray.py
gstaichi/lang/_ndrange.py
gstaichi/lang/_template_mapper.py
gstaichi/lang/_template_mapper_hotpath.py
gstaichi/lang/_wrap_inspect.py
gstaichi/lang/any_array.py
gstaichi/lang/common_ops.py
gstaichi/lang/exception.py
gstaichi/lang/expr.py
gstaichi/lang/field.py
gstaichi/lang/func.py
gstaichi/lang/impl.py
gstaichi/lang/kernel.py
gstaichi/lang/kernel_arguments.py
gstaichi/lang/kernel_impl.py
gstaichi/lang/matrix.py
gstaichi/lang/matrix_ops.py
gstaichi/lang/matrix_ops_utils.py
gstaichi/lang/mesh.py
gstaichi/lang/misc.py
gstaichi/lang/ops.py
gstaichi/lang/runtime_ops.py
gstaichi/lang/shell.py
gstaichi/lang/snode.py
gstaichi/lang/source_builder.py
gstaichi/lang/struct.py
gstaichi/lang/util.py
gstaichi/lang/_fast_caching/__init__.py
gstaichi/lang/_fast_caching/args_hasher.py
gstaichi-4.6.0.dist-info/licenses/LICENSE
gstaichi-4.6.0.dist-info/METADATA
gstaichi-4.6.0.dist-info/WHEEL
gstaichi-4.6.0.dist-info/top_level.txt
gstaichi-4.6.0.dist-info/RECORD
