Metadata-Version: 2.1
Name: gstaichi
Version: 4.6.0
Summary: The GsTaichi Programming Language
Maintainer: GsTaichi developers
License: Apache-2.0
Project-URL: Homepage, https://github.com/Genesis-Embodied-AI/gstaichi
Keywords: graphics,simulation
Classifier: Development Status :: 5 - Production/Stable
Classifier: Topic :: Software Development :: Compilers
Classifier: Topic :: Multimedia :: Graphics
Classifier: Topic :: Games/Entertainment :: Simulation
Classifier: Intended Audience :: Science/Research
Classifier: Intended Audience :: Developers
Classifier: Programming Language :: Python :: 3.10
Classifier: Programming Language :: Python :: 3.11
Classifier: Programming Language :: Python :: 3.12
Classifier: Programming Language :: Python :: 3.13
Requires-Python: <3.14,>=3.10
License-File: LICENSE
Requires-Dist: numpy>=1.26.0
Requires-Dist: colorama
Requires-Dist: dill
Requires-Dist: pydantic>=2.0.0
Requires-Dist: rich>=1.0.0
Requires-Dist: setuptools>=77.0.0
Requires-Dist: cffi>=1.16.0
